README.md
setup.py
berry_video/__init__.py
berry_video/cron.py
berry_video/drive.py
berry_video/player.py
berry_video.egg-info/PKG-INFO
berry_video.egg-info/SOURCES.txt
berry_video.egg-info/dependency_links.txt
berry_video.egg-info/requires.txt
berry_video.egg-info/top_level.txt
script/berry