Metadata-Version: 2.1
Name: berry_video
Version: 0.0.1
Summary: Tools of berry video
Home-page: UNKNOWN
Author: Mr Menezes
Author-email: sr.tama@outlook.com
License: @copyright
Platform: UNKNOWN
Requires-Python: >=3.5
